MANIFEST.in
README.md
VERSION
requirements.txt
setup.cfg
setup.py
atb/__init__.py
atb/bot.py
atb.egg-info/PKG-INFO
atb.egg-info/SOURCES.txt
atb.egg-info/dependency_links.txt
atb.egg-info/requires.txt
atb.egg-info/top_level.txt