Metadata-Version: 2.1
Name: atb
Version: 0.1.3
Summary: Async Telegram Bot
Home-page: https://github.com/devtud/atb
Author: devtud
Author-email: devtud@gmail.com
License: UNKNOWN
Project-URL: Source, https://github.com/devtud/atb
Keywords: async telegram bot
Platform: UNKNOWN
Classifier: Development Status :: 3 - Alpha
Classifier: Intended Audience :: Developers
Classifier: Topic :: Software Development :: Build Tools
Classifier: License :: OSI Approved :: MIT License
Classifier: Programming Language :: Python :: 3.7
Requires-Python: >=3.7, <4
